djmongoengine/__init__.py
djmongoengine/config.py
djmongoengine/connector.py
djmongoengine/models.py
djmongoengine-1.0.dist-info/METADATA
djmongoengine-1.0.dist-info/WHEEL
djmongoengine-1.0.dist-info/top_level.txt
djmongoengine-1.0.dist-info/RECORD
