Metadata-Version: 2.1
Name: djmongoengine
Version: 1.0
Summary: Application to enhance performance by mongodb engine
Home-page: https://github.com/giorgi94/djmongoengine
Author: Giorgi Kakulashvili
License: MIT
Keywords: django,mongodb,graphql
Platform: OS Independent
Requires-Dist: Django (>=2.0)
Requires-Dist: Pillow (>=5.3.0)
Requires-Dist: mongoengine (>=0.18.2)
Requires-Dist: pymongo (>=3.9.0)
